{
  "fetchedAt": "2026-04-03T07:55:03.948Z",
  "location": {
    "lat": 28.5721,
    "lon": -80.648,
    "name": "Launch Pad 39B, Kennedy Space Center"
  },
  "current": {
    "temperature": 20.9,
    "windSpeed": 12,
    "windGusts": 38.5,
    "cloudCover": 1,
    "precipitation": 0,
    "weatherCode": 0
  },
  "hourly": {
    "time": [
      "2026-04-03T00:00",
      "2026-04-03T01:00",
      "2026-04-03T02:00",
      "2026-04-03T03:00",
      "2026-04-03T04:00",
      "2026-04-03T05:00",
      "2026-04-03T06:00",
      "2026-04-03T07:00",
      "2026-04-03T08:00",
      "2026-04-03T09:00",
      "2026-04-03T10:00",
      "2026-04-03T11:00",
      "2026-04-03T12:00",
      "2026-04-03T13:00",
      "2026-04-03T14:00",
      "2026-04-03T15:00",
      "2026-04-03T16:00",
      "2026-04-03T17:00",
      "2026-04-03T18:00",
      "2026-04-03T19:00",
      "2026-04-03T20:00",
      "2026-04-03T21:00",
      "2026-04-03T22:00",
      "2026-04-03T23:00",
      "2026-04-04T00:00",
      "2026-04-04T01:00",
      "2026-04-04T02:00",
      "2026-04-04T03:00",
      "2026-04-04T04:00",
      "2026-04-04T05:00",
      "2026-04-04T06:00",
      "2026-04-04T07:00",
      "2026-04-04T08:00",
      "2026-04-04T09:00",
      "2026-04-04T10:00",
      "2026-04-04T11:00",
      "2026-04-04T12:00",
      "2026-04-04T13:00",
      "2026-04-04T14:00",
      "2026-04-04T15:00",
      "2026-04-04T16:00",
      "2026-04-04T17:00",
      "2026-04-04T18:00",
      "2026-04-04T19:00",
      "2026-04-04T20:00",
      "2026-04-04T21:00",
      "2026-04-04T22:00",
      "2026-04-04T23:00",
      "2026-04-05T00:00",
      "2026-04-05T01:00",
      "2026-04-05T02:00",
      "2026-04-05T03:00",
      "2026-04-05T04:00",
      "2026-04-05T05:00",
      "2026-04-05T06:00",
      "2026-04-05T07:00",
      "2026-04-05T08:00",
      "2026-04-05T09:00",
      "2026-04-05T10:00",
      "2026-04-05T11:00",
      "2026-04-05T12:00",
      "2026-04-05T13:00",
      "2026-04-05T14:00",
      "2026-04-05T15:00",
      "2026-04-05T16:00",
      "2026-04-05T17:00",
      "2026-04-05T18:00",
      "2026-04-05T19:00",
      "2026-04-05T20:00",
      "2026-04-05T21:00",
      "2026-04-05T22:00",
      "2026-04-05T23:00",
      "2026-04-06T00:00",
      "2026-04-06T01:00",
      "2026-04-06T02:00",
      "2026-04-06T03:00",
      "2026-04-06T04:00",
      "2026-04-06T05:00",
      "2026-04-06T06:00",
      "2026-04-06T07:00",
      "2026-04-06T08:00",
      "2026-04-06T09:00",
      "2026-04-06T10:00",
      "2026-04-06T11:00",
      "2026-04-06T12:00",
      "2026-04-06T13:00",
      "2026-04-06T14:00",
      "2026-04-06T15:00",
      "2026-04-06T16:00",
      "2026-04-06T17:00",
      "2026-04-06T18:00",
      "2026-04-06T19:00",
      "2026-04-06T20:00",
      "2026-04-06T21:00",
      "2026-04-06T22:00",
      "2026-04-06T23:00",
      "2026-04-07T00:00",
      "2026-04-07T01:00",
      "2026-04-07T02:00",
      "2026-04-07T03:00",
      "2026-04-07T04:00",
      "2026-04-07T05:00",
      "2026-04-07T06:00",
      "2026-04-07T07:00",
      "2026-04-07T08:00",
      "2026-04-07T09:00",
      "2026-04-07T10:00",
      "2026-04-07T11:00",
      "2026-04-07T12:00",
      "2026-04-07T13:00",
      "2026-04-07T14:00",
      "2026-04-07T15:00",
      "2026-04-07T16:00",
      "2026-04-07T17:00",
      "2026-04-07T18:00",
      "2026-04-07T19:00",
      "2026-04-07T20:00",
      "2026-04-07T21:00",
      "2026-04-07T22:00",
      "2026-04-07T23:00"
    ],
    "temperature": [
      21.8,
      21.2,
      21.1,
      21.1,
      21,
      20.8,
      20.2,
      19.8,
      21.1,
      23.9,
      24.9,
      25.5,
      26.6,
      27.1,
      27.3,
      27.1,
      26.6,
      26,
      25.1,
      24.2,
      23,
      22.4,
      22,
      21.7,
      21.4,
      21.3,
      20.8,
      20.1,
      19.7,
      19.1,
      18.7,
      18.4,
      19.5,
      23.8,
      25.2,
      26.1,
      26.2,
      26.4,
      25.9,
      26.4,
      26.2,
      25.9,
      24.9,
      23.7,
      22,
      21.5,
      21.5,
      21.5,
      21.5,
      21.2,
      21,
      20.6,
      20.2,
      20.1,
      20.1,
      20,
      21.5,
      24,
      25.5,
      26.6,
      27.5,
      27.6,
      27.9,
      27.5,
      27,
      26.5,
      25.1,
      23.8,
      22.4,
      22,
      22,
      21.8,
      21.4,
      20.2,
      19.8,
      19.6,
      19.4,
      19.1,
      19.1,
      19,
      20,
      22.5,
      24.4,
      26.4,
      28.5,
      28.6,
      27,
      27,
      26.5,
      25.9,
      24,
      22,
      21.5,
      21.2,
      21,
      20.4,
      19.5,
      19.4,
      20.1,
      20,
      19.8,
      20.4,
      20.2,
      20.4,
      20.6,
      20.8,
      20.8,
      20,
      19.5,
      19,
      19,
      19,
      20.5,
      19.4,
      19.2,
      19,
      19,
      18.9,
      18.9,
      19
    ],
    "windSpeed": [
      10.4,
      10.5,
      10.4,
      12,
      12,
      10.8,
      9,
      8.7,
      8.4,
      17.5,
      18.1,
      19.4,
      18.9,
      16.8,
      18,
      18.1,
      19.9,
      21,
      18.9,
      16.2,
      15.6,
      14.9,
      13.6,
      10.8,
      12.2,
      12.1,
      11.4,
      9.2,
      8.5,
      9.2,
      8.4,
      9.1,
      7.2,
      12.1,
      16.4,
      17.8,
      19.9,
      20.2,
      21.4,
      21.9,
      21.7,
      21.5,
      20.3,
      17,
      12,
      11,
      11.2,
      11,
      10.2,
      9.2,
      8.2,
      7.4,
      6.6,
      6.7,
      7.5,
      6.4,
      5.9,
      11.2,
      12.3,
      13.2,
      15.3,
      16.6,
      16.3,
      15.8,
      16.1,
      17.4,
      16.1,
      11.5,
      9.7,
      9.4,
      10.1,
      10.5,
      9.1,
      6,
      5.2,
      5.2,
      4.4,
      3.9,
      3.3,
      2.8,
      4.1,
      1.8,
      2.5,
      3.3,
      5.4,
      8.7,
      12,
      11.2,
      12.7,
      13.5,
      13.7,
      13.4,
      11.5,
      12.6,
      12.2,
      10.1,
      8.8,
      6.5,
      7.4,
      6.4,
      6.5,
      6,
      6.8,
      7.9,
      13.9,
      18.8,
      18.4,
      19.8,
      24.5,
      21.3,
      23.8,
      23.5,
      23.3,
      23.5,
      23.2,
      22.2,
      22.5,
      21,
      18.6,
      17.3
    ],
    "windGusts": [
      36.4,
      38.2,
      37.4,
      37.4,
      38.9,
      36.4,
      34.9,
      32.8,
      32,
      31,
      25.9,
      26.3,
      25.2,
      21.2,
      22.7,
      23,
      25.6,
      28.1,
      26.1,
      25.9,
      34.9,
      35.3,
      36,
      33.1,
      37.1,
      37.8,
      37.1,
      34.6,
      32.4,
      32.4,
      29.2,
      29.2,
      24.1,
      24.1,
      23.4,
      22.3,
      25.6,
      26.3,
      27.7,
      28.4,
      28.4,
      29.5,
      29.2,
      28.3,
      29,
      28.1,
      28.1,
      28.4,
      27,
      25.9,
      24.1,
      21.2,
      18.4,
      18.4,
      22.3,
      15.1,
      20.5,
      18.4,
      15.8,
      14.8,
      15.1,
      15.1,
      14.4,
      13.7,
      13.7,
      15.8,
      19.8,
      19.8,
      24.1,
      26.6,
      27.7,
      27.7,
      25.6,
      13.3,
      8.3,
      6.5,
      4.3,
      4,
      3.2,
      2.9,
      5,
      1.1,
      2.2,
      4,
      3.6,
      5.4,
      7.2,
      9,
      12.6,
      13.3,
      16.2,
      22,
      23,
      25.6,
      27.4,
      23.4,
      23.4,
      20.2,
      20.9,
      19.1,
      14,
      15.1,
      19.4,
      22,
      27.4,
      31.7,
      35.6,
      37.8,
      42.5,
      42.1,
      45,
      43.9,
      41.8,
      41,
      41.4,
      41,
      42.8,
      41.4,
      39.6,
      38.5
    ],
    "precipitationProbability": [
      0,
      3,
      7,
      4,
      4,
      3,
      3,
      1,
      0,
      0,
      0,
      0,
      1,
      0,
      0,
      0,
      2,
      1,
      2,
      2,
      2,
      1,
      0,
      1,
      1,
      3,
      1,
      0,
      1,
      0,
      0,
      0,
      0,
      0,
      1,
      0,
      2,
      0,
      1,
      5,
      5,
      5,
      5,
      5,
      5,
      3,
      3,
      3,
      3,
      3,
      3,
      5,
      5,
      5,
      5,
      5,
      5,
      13,
      13,
      13,
      13,
      13,
      13,
      24,
      24,
      24,
      24,
      24,
      24,
      24,
      24,
      24,
      24,
      24,
      24,
      14,
      14,
      14,
      14,
      14,
      14,
      23,
      23,
      23,
      23,
      23,
      23,
      51,
      51,
      51,
      51,
      51,
      51,
      50,
      50,
      50,
      50,
      50,
      50,
      50,
      50,
      50,
      50,
      50,
      50,
      59,
      59,
      59,
      59,
      59,
      59,
      50,
      50,
      50,
      50,
      50,
      50,
      32,
      32,
      32
    ]
  },
  "daily": {
    "time": [
      "2026-04-03",
      "2026-04-04",
      "2026-04-05",
      "2026-04-06",
      "2026-04-07"
    ],
    "weatherCode": [
      2,
      3,
      51,
      55,
      80
    ],
    "temperatureMax": [
      27.3,
      26.4,
      27.9,
      28.6,
      20.8
    ],
    "temperatureMin": [
      19.8,
      18.4,
      20,
      19,
      18.9
    ],
    "windSpeedMax": [
      21,
      21.9,
      17.4,
      13.7,
      24.5
    ],
    "precipitationProbabilityMax": [
      7,
      5,
      24,
      51,
      59
    ]
  },
  "solar": {
    "kpIndex": 3.67,
    "kpTimestamp": "2026-04-03T03:00:00",
    "solarWindSpeed": 633.3,
    "solarWindDensity": 0.27
  }
}